AUTHORS.rst
CONTRIBUTING.rst
HISTORY.rst
LICENSE
MANIFEST.in
README.rst
setup.cfg
setup.py
autopep8_autoline/__init__.py
autopep8_autoline.egg-info/PKG-INFO
autopep8_autoline.egg-info/SOURCES.txt
autopep8_autoline.egg-info/dependency_links.txt
autopep8_autoline.egg-info/entry_points.txt
autopep8_autoline.egg-info/not-zip-safe
autopep8_autoline.egg-info/requires.txt
autopep8_autoline.egg-info/top_level.txt
tests/__init__.py
tests/test_autopep8_autoline.py